vscode_command_client/__init__.py
vscode_command_client/cli.py
vscode_command_client/client.py
vscode_command_client-1.0.0.dist-info/METADATA
vscode_command_client-1.0.0.dist-info/WHEEL
vscode_command_client-1.0.0.dist-info/entry_points.txt
vscode_command_client-1.0.0.dist-info/licenses/LICENSE
vscode_command_client-1.0.0.dist-info/RECORD
