Metadata-Version: 2.4
Name: vscode-command-client
Version: 1.0.0
Summary: Python client for VSCode Command Server extension
Project-URL: Homepage, https://github.com/crimson206/run-extension
Project-URL: Repository, https://github.com/crimson206/run-extension
Project-URL: Documentation, https://github.com/crimson206/run-extension#readme
Project-URL: Bug Tracker, https://github.com/crimson206/run-extension/issues
Author-email: Sisung Kim <sisung.kim1@gmail.com>
License: MIT License
License-File: LICENSE
Keywords: api,automation,client,command,server,vscode
Requires-Python: >=3.8
Requires-Dist: requests>=2.25.0
